Metadata-Version: 2.1
Name: xplore
Version: 0.0.1
Summary: A python package built with pandas for data scientist/analysts, AI/ML engineers for exploring features of a dataset in minimal number of lines of code for quick analysis before data wrangling and feature extraction.
Home-page: https://github.com/buabaj/xplore
Author: Jerry Buaba
Author-email: buabajerry@gmail.com
License: UNKNOWN
Download-URL: https://github.com/buabaj/xplore/archive/v0.0.1.tar.gz
Keywords: Data-Science,Machine-Learning,python
Platform: UNKNOWN
Classifier: Programming Language :: Python :: 3
Classifier: License :: OSI Approved :: MIT License
Classifier: Operating System :: OS Independent
Requires-Python: >=3.6
